<?xml version="1.0"?>
<extensions>
	
	<details>
		<title lang="EN">Paul Webster's Squeezecenter Plugin for Radio France</title>
	</details>
	
	<plugins>
		
		<plugin name="RadioFrance" version="0.1.26" minTarget="7.4" maxTarget="*">
			<title lang="EN">Radio France</title>
			<desc  lang="EN">Radio France track information</desc>
			<desc  lang="FR">Radio France - info sur le morceau de musique</desc>
			<creator>Paul Webster</creator>
			<email></email>
			<changes lang="EN">
				- Add another way to get programme art
				- Update default images for stations
			</changes>
			<changes lang="FR">
				- Ajouter un autre moyen d'obtenir de l'art de programme
				- Mettre à jour les images par défaut pour les stations
			</changes>
			<url>https://paulwebster.github.io/RadioFrance/RadioFrance-0.1.26.zip</url>
			<sha>7fe802db1b5aad469059f39640ead3b5b6fd7257</sha>
		</plugin>

	</plugins>
	
</extensions>

